requests2hdd/README.MD
requests2hdd/__init__.py
requests2hdd/requirements.txt
requests2hdd/thirdparty.json
requests2hdd-0.10.dist-info/LICENSE.rst
requests2hdd-0.10.dist-info/METADATA
requests2hdd-0.10.dist-info/WHEEL
requests2hdd-0.10.dist-info/top_level.txt
requests2hdd-0.10.dist-info/RECORD
