Metadata-Version: 2.1
Name: requests2hdd
Version: 0.10
Summary: downloads files from a URL, creates the same folder structure on the HDD as the URL has, and saves the file
Home-page: https://github.com/hansalemaos/requests2hdd
Author: Johannes Fischer
Author-email: aulasparticularesdealemaosp@gmail.com
License: MIT
Keywords: requests
Classifier: Development Status :: 4 - Beta
Classifier: Programming Language :: Python :: 3 :: Only
Classifier: Programming Language :: Python :: 3.10
Classifier: Topic :: Software Development :: Libraries :: Python Modules
Classifier: Topic :: Utilities
License-File: LICENSE.rst
Requires-Dist: requests
Requires-Dist: touchtouch
Requires-Dist: windows-filepath
